README.md
setup.py
newrelic_deploy/__init__.py
newrelic_deploy.egg-info/PKG-INFO
newrelic_deploy.egg-info/SOURCES.txt
newrelic_deploy.egg-info/dependency_links.txt
newrelic_deploy.egg-info/entry_points.txt
newrelic_deploy.egg-info/requires.txt
newrelic_deploy.egg-info/top_level.txt